mcp_server/__init__.py
mcp_server/server.py
mcp_server/entities/flow.py
mcp_server/entities/ifly_client.py
iflow_mcp_iflytek_ifly_workflow_mcp_server-1.0.0.dist-info/METADATA
iflow_mcp_iflytek_ifly_workflow_mcp_server-1.0.0.dist-info/WHEEL
iflow_mcp_iflytek_ifly_workflow_mcp_server-1.0.0.dist-info/entry_points.txt
iflow_mcp_iflytek_ifly_workflow_mcp_server-1.0.0.dist-info/licenses/LICENSE
iflow_mcp_iflytek_ifly_workflow_mcp_server-1.0.0.dist-info/RECORD
