Metadata-Version: 2.4
Name: iflow-mcp_iflytek_ifly-workflow-mcp-server
Version: 1.0.0
Summary: This a simple implementation of an MCP server using iFlytek. It enables calling iFlytek workflows through MCP tools.
License-File: LICENSE
Requires-Python: >=3.11
Requires-Dist: httpx==0.28.1
Requires-Dist: mcp==1.5.0
Requires-Dist: pip==25.0.1
Requires-Dist: pytest==8.3.5
Requires-Dist: python-dotenv==1.0.1
Requires-Dist: pyyaml==6.0.2
Requires-Dist: requests==2.32.3
